ts_scan/__init__.py
ts_scan/api.py
ts_scan/analyse/__init__.py
ts_scan/analyse/scanoss.py
ts_scan/analyse/gitignore/Node.gitignore
ts_scan/analyse/gitignore/Python.gitignore
ts_scan/cli/__init__.py
ts_scan/cli/analyse.py
ts_scan/cli/check.py
ts_scan/cli/convert.py
ts_scan/cli/import_sbom.py
ts_scan/cli/init.py
ts_scan/cli/scan.py
ts_scan/cli/upload.py
ts_scan/cyclonedx/__init__.py
ts_scan/pm/__init__.py
ts_scan/pm/gradle.py
ts_scan/pm/node.py
ts_scan/pm/nuget.py
ts_scan/pm/pypi.py
ts_scan/pm/maven/__init__.py
ts_scan/pm/maven/__main__.py
ts_scan/pm/maven/pom_utils.py
ts_scan/pm/maven/tree_utils.py
ts_scan/pm/syft/__init__.py
ts_scan/pm/syft/model.py
ts_scan/pm/syft/schema-16.0.18.json
ts_scan/spdx/__init__.py
ts_scan-1.6.0.dist-info/licenses/LICENSE
ts_scan-1.6.0.dist-info/METADATA
ts_scan-1.6.0.dist-info/WHEEL
ts_scan-1.6.0.dist-info/entry_points.txt
ts_scan-1.6.0.dist-info/top_level.txt
ts_scan-1.6.0.dist-info/RECORD
