Metadata-Version: 2.4
Name: ts-scan
Version: 1.6.0
Summary: TrustSource Packages Scanner
Author: EACG GmbH
License-Expression: Apache-2.0
Project-URL: Homepage, https://github.com/trustsource/ts-scan.git
Keywords: dependencies,modules,compliance,TrustSource
Requires-Python: >=3.10
License-File: LICENSE
Requires-Dist: defusedxml~=0.7.1
Requires-Dist: semantic_version~=2.10.0
Requires-Dist: build~=1.2.2
Requires-Dist: importlib-metadata~=8.6.0
Requires-Dist: requests~=2.32.3
Requires-Dist: ts-deepscan~=2.3.0
Requires-Dist: spdx-tools>=0.8.2
Requires-Dist: click==8.1.7
Requires-Dist: click-params~=0.5.0
Requires-Dist: license-expression~=30.4.0
Requires-Dist: packageurl-python~=0.16.0
Requires-Dist: wasabi~=1.1.3
Requires-Dist: dataclasses-json~=0.6.7
Requires-Dist: cyclonedx-python-lib~=8.5.0
Requires-Dist: shippinglabel~=2.1.0
Requires-Dist: tqdm~=4.67.0
Requires-Dist: scanoss~=1.20.4
Requires-Dist: toml~=0.10.2
Dynamic: license-file
